idsignal/__init__.py
idsignal/signal.py
idsignal-0.1.0.dist-info/licenses/LICENCE
idsignal-0.1.0.dist-info/METADATA
idsignal-0.1.0.dist-info/WHEEL
idsignal-0.1.0.dist-info/top_level.txt
idsignal-0.1.0.dist-info/RECORD
