Metadata-Version: 2.4
Name: idsignal
Version: 0.1.0
Summary: A python module with tools which can be used to add signaling between different components.
Author-email: Improper Decoherence <improper.decoherence@proton.me>
License: MIT License
Project-URL: Homepage, https://codeberg.org/decoherence/idsignal
Classifier: Programming Language :: Python :: 3
Classifier: License :: OSI Approved :: MIT License
Classifier: Operating System :: OS Independent
Requires-Python: >=3.12
License-File: LICENCE
Provides-Extra: test
Requires-Dist: pytest>=8.4; extra == "test"
Dynamic: license-file
